httpc/__init__.py
httpc/__main__.py
httpc/_api.py
httpc/_base.py
httpc/_broadcaster.py
httpc/_client.py
httpc/_next_data.py
httpc/_parse.py
httpc/py.typed
httpc/catcher/__init__.py
httpc/catcher/__main__.py
httpc/catcher/_catcher.py
httpc/catcher/_db.py
httpc/catcher/py.typed
httpc-0.13.0.dist-info/METADATA
httpc-0.13.0.dist-info/WHEEL
httpc-0.13.0.dist-info/entry_points.txt
httpc-0.13.0.dist-info/licenses/LICENSE
httpc-0.13.0.dist-info/RECORD
