Metadata-Version: 2.4
Name: httpc
Version: 0.13.0
Summary: httpx with css.
Author-email: ilotoki0804 <ilotoki0804@gmail.com>
License-Expression: Apache-2.0
License-File: LICENSE
Keywords: catcher,css,httpx,request,selectolax,soup
Classifier: Intended Audience :: Developers
Classifier: License :: OSI Approved :: Apache Software License
Classifier: Operating System :: OS Independent
Classifier: Programming Language :: Python :: 3
Classifier: Programming Language :: Python :: 3.10
Classifier: Programming Language :: Python :: 3.11
Classifier: Programming Language :: Python :: 3.12
Classifier: Programming Language :: Python :: 3.13
Requires-Python: >=3.10
Requires-Dist: httpx>=0.28.0
Requires-Dist: selectolax>=0.3.26
Provides-Extra: catcher
Requires-Dist: zstd>=1.5.6.6; extra == 'catcher'
